safepython/__init__.py
safepython/EET.py
safepython/FAST.py
safepython/HBV.py
safepython/HyMod.py
safepython/ishigami_homma.py
safepython/lhcube.py
safepython/model_execution.py
safepython/PAWN.py
safepython/plot_functions.py
safepython/RSA_groups.py
safepython/RSA_thres.py
safepython/sampling.py
safepython/sobol_g.py
safepython/util.py
safepython/VBSA.py
safepython-0.2.0.dist-info/METADATA
safepython-0.2.0.dist-info/WHEEL
safepython-0.2.0.dist-info/RECORD
