Metadata-Version: 2.1
Name: SAFEpython
Version: 0.2.0
Summary: A Python implementation of the SAFE toolbox for sensitivity analysis
Home-page: https://github.com/SAFEtoolbox/SAFE-python
License: GPL-3.0
Author: Francesca Pianosi, Fanny Sarrazin, Thorsten Wagener
Author-email: fanny.sarrazin@inrae.fr
Requires-Python: >=3.7,<4
Classifier: License :: OSI Approved :: GNU General Public License v3 (GPLv3)
Classifier: Programming Language :: Python :: 3
Classifier: Programming Language :: Python :: 3.7
Classifier: Programming Language :: Python :: 3.8
Classifier: Programming Language :: Python :: 3.9
Classifier: Programming Language :: Python :: 3.10
Classifier: Programming Language :: Python :: 3.11
Classifier: Programming Language :: Python :: 3.12
Requires-Dist: matplotlib (>=2.2.3)
Requires-Dist: numpy (>=1.19.2)
Requires-Dist: scipy (>=1.3.0)
Project-URL: Documentation, https://safetoolbox.github.io
Project-URL: Repository, https://github.com/SAFEtoolbox/SAFE-python
